sibila/__init__.py
sibila/anthropic.py
sibila/cli.py
sibila/gen.py
sibila/json_grammar.py
sibila/json_schema.py
sibila/llamacpp.py
sibila/mistral.py
sibila/model.py
sibila/models.py
sibila/multigen.py
sibila/null.py
sibila/openai.py
sibila/schema_format_openai.py
sibila/text_splitter.py
sibila/thread.py
sibila/tools.py
sibila/utils.py
sibila/res/__init__.py
sibila/res/base_formats.json
sibila/res/base_models.json
sibila-0.4.5.dist-info/LICENSE
sibila-0.4.5.dist-info/METADATA
sibila-0.4.5.dist-info/WHEEL
sibila-0.4.5.dist-info/entry_points.txt
sibila-0.4.5.dist-info/top_level.txt
sibila-0.4.5.dist-info/RECORD
