Metadata-Version: 2.1
Name: sibila
Version: 0.4.5
Summary: Structured queries from local or online LLM models
Author-email: Jorge Diogo <jndiogo@gmail.com>
License: MIT
Project-URL: Homepage, https://github.com/jndiogo/sibila
Project-URL: Documentation, https://jndiogo.github.io/sibila
Project-URL: Issues, https://github.com/jndiogo/sibila/issues
Keywords: llama.cpp,AI,Transformers,GPT,LLM
Classifier: Programming Language :: Python :: 3
Classifier: Programming Language :: Python :: 3.9
Classifier: Programming Language :: Python :: 3.10
Classifier: Programming Language :: Python :: 3.11
Classifier: Programming Language :: Python :: 3.12
Classifier: Programming Language :: Python :: 3.13
Classifier: License :: OSI Approved :: MIT License
Classifier: Operating System :: OS Independent
Classifier: Topic :: Scientific/Engineering :: Artificial Intelligence
Requires-Python: >=3.9
License-File: LICENSE
Requires-Dist: llama-cpp-python >=0.2
Requires-Dist: openai >=1.1
Requires-Dist: tiktoken
Requires-Dist: anthropic
Requires-Dist: mistralai
Requires-Dist: jinja2 >=3.0
Requires-Dist: jsonschema
Requires-Dist: pydantic >=2.0
Requires-Dist: typing-extensions
Requires-Dist: tqdm
Requires-Dist: pytest-asyncio >=0.17
